cryptrooper/__init__.py
cryptrooper-0.1.dist-info/LICENSE
cryptrooper-0.1.dist-info/METADATA
cryptrooper-0.1.dist-info/WHEEL
cryptrooper-0.1.dist-info/top_level.txt
cryptrooper-0.1.dist-info/RECORD
