Metadata-Version: 2.1
Name: cryptrooper
Version: 0.1
Summary: A module to encode and decode your text with a key
Home-page: https://github.com/sprin-g-reen/cryptrooper
Author: Parvat
Author-email: replyerrors.parvat@gmail.com
License: UNKNOWN
Project-URL: Bug Tracker, https://github.com/sprin-g-reen/cryptrooper/issues
Platform: UNKNOWN
Classifier: Programming Language :: Python :: 3
Classifier: License :: OSI Approved :: MIT License
Classifier: Operating System :: OS Independent
Requires-Python: >=3.6
License-File: LICENSE
